unitspy/__init__.py
unitspy-2.0.1.dist-info/METADATA
unitspy-2.0.1.dist-info/WHEEL
unitspy-2.0.1.dist-info/licenses/LICENSE
unitspy-2.0.1.dist-info/RECORD
