Metadata-Version: 2.1
Name: unitspy
Version: 2.0.1
Summary: A Python library that makes it easier to work with units in physics
Project-URL: Homepage, https://github.com/GustavLindberg99/Units.py
Project-URL: Bug Tracker, https://github.com/GustavLindberg99/Units.py/issues
Author: Gustav Lindberg
License-File: LICENSE
Classifier: License :: OSI Approved :: Apache Software License
Classifier: Operating System :: OS Independent
Classifier: Programming Language :: Python :: 3
Requires-Python: >=3.10
Requires-Dist: typeguard
